{
  "basics": {
    "name": "Jo Doe",
    "label": "Lorem Ipsum Architect",
    "image": "",
    "email": "jo.doe@example.com",
    "phone": "(555) 555-5555",
    "url": "https://example.com",
    "summary": "Lorem ipsum dolor sit amet, consectetur adipiscing elit. Proin interdum purus ut diam tincidunt sollicitudin.",
    "location": {
      "address": "1234 Lorem Ipsum St",
      "postalCode": "12345",
      "city": "Dolor",
      "countryCode": "US",
      "region": "Amet"
    },
    "profiles": [
      {
        "network": "github",
        "username": "jo-doe",
        "url": "https://github.com/example",
        "display": "github.com/example"
      },
      {
        "network": "linkedin",
        "username": "jo-doe",
        "url": "https://linkedin.com/in/example",
        "display": "linkedin.com/in/example"
      }
    ]
  },
  "work": [
    {
      "name": "Company Ipsum",
      "position": "Senior Architect",
      "startDate": "2020-01-01",
      "endDate": "Present",
      "summary": "Curabitur eleifend lacus ac nisl fermentum, a feugiat neque dictum.",
      "highlights": [
        "Integer facilisis quam id augue fermentum, sit amet aliquet est posuere.",
        "Donec nec odio nec metus sollicitudin facilisis in vel purus.",
        "Mauris et ligula eu risus laoreet dapibus ac id massa.",
        "Praesent volutpat sapien eu libero sodales dictum."
      ]
    },
    {
      "name": "Lorem Tech",
      "position": "Lead Engineer",
      "startDate": "2015-01-01",
      "endDate": "2019-12-31",
      "summary": "Etiam nec mi vitae magna vehicula aliquet.",
      "highlights": [
        "Vestibulum non elit a magna pharetra pulvinar.",
        "Aliquam tristique libero at mi vehicula, nec aliquet eros eleifend.",
        "Aenean varius turpis in mi faucibus sagittis.",
        "Ut ut justo non ligula luctus cursus sit amet a felis."
      ]
    },
    {
      "name": "Lorem Tech",
      "position": "Lead Engineer",
      "startDate": "2015-01-01",
      "endDate": "2013-01-011",
      "summary": "Etiam nec mi vitae magna vehicula aliquet.",
      "highlights": [
        "Vestibulum non elit a magna pharetra pulvinar.",
        "Aliquam tristique libero at mi vehicula, nec aliquet eros eleifend.",
        "Aenean varius turpis in mi faucibus sagittis.",
        "Ut ut justo non ligula luctus cursus sit amet a felis."
      ]
    }
  ],
  "skills": [
    {
      "name": "Development",
      "level": "Expert",
      "keywords": [
        "HTML, CSS, JavaScript",
        "React, Angular, Vue",
        "Backend Frameworks"
      ]
    },
    {
      "name": "Cloud Platforms",
      "level": "Advanced",
      "keywords": [
        "AWS, Azure, GCP",
        "Containerization",
        "CI/CD Processes"
      ]
    }
  ],
  "languages": [
    {
      "language": "English",
      "fluency": "Native"
    }
  ],
  "interests": [
    {
      "name": "Hiking",
      "keywords": [
        "trails",
        "outdoors"
      ]
    },
    {
      "name": "Reading",
      "keywords": [
        "fiction",
        "non-fiction"
      ]
    }
  ],
  "projects": [
    {
      "name": "Sample Project",
      "image": "sample.jpg",
      "startDate": "2020-01-01",
      "endDate": "2021-01-01",
      "description": "Aenean commodo justo eu neque dignissim, nec ultricies nulla tincidunt.",
      "highlights": [
        "Morbi ac orci sed odio consequat sollicitudin.",
        "Vestibulum vitae lorem quis velit varius vulputate."
      ],
      "url": "https://example.com"
    }
  ]
}